pyshamir/__init__.py
pyshamir/_utils.py
pyshamir/shamir.py
pyshamir-1.0.4.dist-info/METADATA
pyshamir-1.0.4.dist-info/WHEEL
pyshamir-1.0.4.dist-info/top_level.txt
pyshamir-1.0.4.dist-info/RECORD
