Metadata-Version: 2.1
Name: pyshamir
Version: 1.0.4
Summary: Python port of Shamir key Split and Combine methods from Hashicorp Vault.
Home-page: https://github.com/konidev20/pyshamir
Author: Srigovind Nayak
Author-email: sgovind.dev@outlook.com
Maintainer: Srigovind Nayak
Maintainer-email: sgovind.dev@outlook.com
Project-URL: Documentation, https://github.com/konidev20/pyshamir
Project-URL: Source Code, https://github.com/konidev20/pyshamir
Project-URL: Issue Tracker, https://github.com/konidev20/pyshamir/issues
Keywords: shamir,pyshamir
Classifier: Development Status :: 5 - Production/Stable
Classifier: Intended Audience :: Developers
Classifier: License :: OSI Approved :: MIT License
Classifier: Operating System :: OS Independent
Classifier: Programming Language :: Python :: 3.7
Classifier: Programming Language :: Python :: 3.8
Classifier: Programming Language :: Python :: 3.9
Classifier: Programming Language :: Python :: 3.10
Classifier: Topic :: Security :: Cryptography
Classifier: Topic :: Software Development :: Libraries :: Python Modules
Requires-Python: >=3.7
